jwt-stubs/METADATA.toml
jwt-stubs/__init__.pyi
jwt-stubs/algorithms.pyi
jwt-stubs/contrib/__init__.pyi
jwt-stubs/contrib/algorithms/__init__.pyi
jwt-stubs/contrib/algorithms/py_ecdsa.pyi
jwt-stubs/contrib/algorithms/pycrypto.pyi
types_PyJWT-1.7.1.dist-info/METADATA
types_PyJWT-1.7.1.dist-info/WHEEL
types_PyJWT-1.7.1.dist-info/top_level.txt
types_PyJWT-1.7.1.dist-info/RECORD
