Metadata-Version: 2.1
Name: types-PyJWT
Version: 1.7.1
Summary: Typing stubs for PyJWT
Home-page: https://github.com/python/typeshed
License: Apache-2.0 license
Platform: UNKNOWN
Classifier: License :: OSI Approved :: Apache Software License
Classifier: Typing :: Typed
